rdmc/__init__.py
rdmc/conf.py
rdmc/forcefield.py
rdmc/plotter.py
rdmc/reaction.py
rdmc/utils.py
rdmc/conformer_generation/__init__.py
rdmc/conformer_generation/align.py
rdmc/conformer_generation/generators.py
rdmc/conformer_generation/metrics.py
rdmc/conformer_generation/sampler.py
rdmc/conformer_generation/solvation.py
rdmc/conformer_generation/ts_generators.py
rdmc/conformer_generation/utils.py
rdmc/conformer_generation/comp_env/__init__.py
rdmc/conformer_generation/comp_env/ase.py
rdmc/conformer_generation/comp_env/gaussian.py
rdmc/conformer_generation/comp_env/gsm.py
rdmc/conformer_generation/comp_env/orca.py
rdmc/conformer_generation/comp_env/pyg.py
rdmc/conformer_generation/comp_env/qchem.py
rdmc/conformer_generation/comp_env/sella.py
rdmc/conformer_generation/comp_env/software.py
rdmc/conformer_generation/comp_env/torch.py
rdmc/conformer_generation/comp_env/ts_ml.py
rdmc/conformer_generation/comp_env/xtb/__init__.py
rdmc/conformer_generation/comp_env/xtb/crest.py
rdmc/conformer_generation/comp_env/xtb/opt.py
rdmc/conformer_generation/comp_env/xtb/utils.py
rdmc/conformer_generation/embedders/__init__.py
rdmc/conformer_generation/embedders/base.py
rdmc/conformer_generation/embedders/etkdg.py
rdmc/conformer_generation/embedders/geomol.py
rdmc/conformer_generation/embedders/random.py
rdmc/conformer_generation/embedders/torsional_diffusion.py
rdmc/conformer_generation/optimizers/__init__.py
rdmc/conformer_generation/optimizers/base.py
rdmc/conformer_generation/optimizers/gaussian.py
rdmc/conformer_generation/optimizers/mmff.py
rdmc/conformer_generation/optimizers/orca.py
rdmc/conformer_generation/optimizers/qchem.py
rdmc/conformer_generation/optimizers/xtb.py
rdmc/conformer_generation/pruners/__init__.py
rdmc/conformer_generation/pruners/base.py
rdmc/conformer_generation/pruners/crest.py
rdmc/conformer_generation/pruners/torsion.py
rdmc/conformer_generation/task/__init__.py
rdmc/conformer_generation/task/basetask.py
rdmc/conformer_generation/task/gaussian.py
rdmc-1.0.0.dist-info/licenses/LICENSE
rdmc-1.0.0.dist-info/METADATA
rdmc-1.0.0.dist-info/WHEEL
rdmc-1.0.0.dist-info/top_level.txt
rdmc-1.0.0.dist-info/RECORD
