Metadata-Version: 2.4
Name: RDMC
Version: 1.0.0
Summary: A light-weight software package with expertise in handling Reaction Data and Molecular (including transitions states) Conformers.
Author: Lagnajit Pattanaik, Shih-Cheng Li, Kevin Spiekermann, Hao-Wei Pang, Jonathan Zheng
Author-email: Xiaorui Dong <xiaorui@mit.com>, "William H. Green" <whgreen@mit.edu>
License: 
Project-URL: Homepage, https://github.com/xiaoruiDong/RDMC
Keywords: chemistry,RDKit,molecule,conformer,reaction,cheminformatics
Classifier: Programming Language :: Python :: 3
Classifier: License :: OSI Approved :: MIT License
Classifier: Operating System :: OS Independent
Classifier: Topic :: Scientific/Engineering :: Chemistry
Requires-Python: >=3.9
License-File: LICENSE
Requires-Dist: rdkit>=2021.03.1
Requires-Dist: numpy
Requires-Dist: scipy
Requires-Dist: openbabel-wheel>=3.1.1
Requires-Dist: networkx
Requires-Dist: matplotlib
Requires-Dist: cclib
Requires-Dist: py3Dmol
Requires-Dist: ipywidgets
Requires-Dist: ase
Provides-Extra: dev
Requires-Dist: ruff; extra == "dev"
Requires-Dist: pydocstyle; extra == "dev"
Requires-Dist: docformatter; extra == "dev"
Requires-Dist: pydoclint; extra == "dev"
Requires-Dist: pre-commit; extra == "dev"
Requires-Dist: mypy; extra == "dev"
Requires-Dist: pytest-cov; extra == "dev"
Requires-Dist: pytest; extra == "dev"
Requires-Dist: nbmake; extra == "dev"
Provides-Extra: docs
Requires-Dist: sphinx; extra == "docs"
Requires-Dist: pydata-sphinx-theme; extra == "docs"
Requires-Dist: sphinx-favicon; extra == "docs"
Dynamic: license-file
